edge_det.v
module edge_det #(parameter
									type=0
								 )
			 (
				 input wire clk,
				 input wire sgn,
				 output wire out
			 );

reg sgn_pre = 0;

always @(posedge clk) begin
	if (sgn_changed) sgn_pre <= sgn;
end

assign sgn_changed = sgn ^ sgn_pre,
			 pos_edge = (type == 0) & (sgn & sgn_changed),
			 neg_edge = (type == 1) & (~sgn & sgn_changed),
			 both_edges = (type == 2) & sgn_changed,
			 out = pos_edge | neg_edge | both_edges;

endmodule

pwm.v
module pwm #(parameter
						 clk_mhz = 50,
						 freq_khz = 400,
						 duty = 40
						)
			 (
				 input wire clk,
				 input wire rst,
				 output wire out
			 );


function[31:0] div(input[31:0] A, input[31:0] B);
	begin
		div = A / B + (2*(A % B) >= B ? 1 : 0);
	end
endfunction

localparam clk_khz = 1000 * clk_mhz,
					 cnt_max = div(clk_khz, freq_khz),
					 cnt_width = $clog2(cnt_max),
					 cnt_duty = div(duty * cnt_max, 100);

reg[cnt_width-1:0] cnt = 0;

always @(posedge clk) begin
	cnt <= (~rst & (cnt < cnt_max-1)) ? cnt + 1 : 0;
end

assign out = cnt < cnt_duty;

endmodule

entry.v
/*
module entry(
				 input wire clk,
				 input wire data,
				 output reg out
			 );
 
localparam baudrate = 100_000,
					 f_clk = 50_000_000,
					 cnt_val = f_clk/(2*baudrate)-1;
 
reg isTransmit = 0;
reg data_pre = 1;
reg[13:0] cnt = cnt_val;
reg[9:0] sh_reg = 0;
 
reg[4:0] cnt2 = 0;
 
 
always @(posedge clk) begin
	if (data_negedge) begin
		data_pre <= data;
		if (~isTransmit) begin
			isTransmit <= 1;
			cnt <= 3*cnt_val;
		end
		else cnt <= cnt_val;
	end
	else if (data_posedge) begin
		data_pre <= data;
		cnt <= cnt_val;
	end
	else cnt <= cnt - 1;
end
 
always @(posedge clk) begin
	if (check) begin
		sh_reg <= sh_reg << 1;
		sh_reg[0] <= data;
	end
end
 
always @(posedge clk) begin
	if (cnt2 == 0) begin
		cnt2 <= 10 + 10*sh_reg;
		out <= out ^ 1;
	end
	else cnt2 <= cnt2 - 1;
end
 
 
assign data_posedge = data && ~data_pre;
assign data_negedge = ~data && data_pre;
assign check = isTransmit && (cnt == 0);
 
endmodule
*/


/*
module entry #(parameter width=8) (
				 input wire clk,
				 input wire data,
				 output reg[width-1:0] sh_reg
			 );
 
 
 
 
 
always @(posedge clk) begin
	sh_reg <= {sh_reg[width-2:0], data};
end
 
endmodule
*/

`include "pwm.v"
`include "edge_det.v"

module entry (
				 input wire clk,
				 input wire data,
				 output wire out,
				 output wire out2
			 );

wire clk_uart,
		 edges,
		 neg_egde_det_out;

reg zero = 0;

pwm #(.freq_khz(1000), .duty(50)) pwm_ins(.clk(clk), .rst(zero), .out(clk_uart));
edge_det #(.type(2)) edge_det_ins(.clk(clk), .sgn(clk_uart), .out(edges));
edge_det #(.type(1)) neg_edge_det(.clk(clk), .sgn(clk_uart), .out(neg_egde_det_out));

always @(posedge clk) begin

end

assign out = clk_uart,
			 out2 = edges;

endmodule

tb.v
`include "entry.v"

module test_entry;

reg tclk, tdata;
wire tout;

//устанавливаем экземпляр тестируемого модуля
entry entry_inst(tclk, tdata, tout);

//моделируем сигнал тактовой частоты
always #10 tclk = ~tclk;

//от начала времени...

initial begin
	tclk = 0;
	tdata = 0;

	//через временной интервал "50" подаем сигнал сброса
	#55 tdata = 1;
	#50 tdata = 0;
	#50 tdata = 1;
	#50 tdata = 0;
end

//заканчиваем симуляцию в момент времени "400"
initial begin
	#400 $finish;
end

//создаем файл VCD для последующего анализа сигналов
initial begin
	$dumpfile("out.vcd");
	$dumpvars(0,test_entry);
end

//наблюдаем на некоторыми сигналами системы
initial $monitor($stime,, tclk,,, tdata,, tout);

endmodule

out.vcd
$date
	Mon Nov 25 20:42:27 2019
$end
$version
	Icarus Verilog
$end
$timescale
	1s
$end
$scope module test_entry $end
$var wire 1 ! tout $end
$var reg 1 " tclk $end
$var reg 1 # tdata $end
$scope module entry_inst $end
$var wire 1 " clk $end
$var wire 1 # data $end
$var reg 1 ! out $end
$upscope $end
$upscope $end
$enddefinitions $end
#0
$dumpvars
0#
0"
x!
$end
#10
0!
1"
#20
0"
#30
1"
#40
0"
#50
1"
#55
1#
#60
0"
#70
1!
1"
#80
0"
#90
1"
#100
0"
#105
0#
#110
0!
1"
#120
0"
#130
1"
#140
0"
#150
1"
#155
1#
#160
0"
#170
1!
1"
#180
0"
#190
1"
#200
0"
#205
0#
#210
0!
1"
