cnt.v
module cnt(
				 input wire clk,
				 input wire rst,
				 output reg[7:0] out = 0
			 );

always @(posedge clk or posedge rst) begin
	if (rst) out <= 0;
	else if (clk) out <= out + 1;
end


endmodule

edge_det.v
module edge_det #(parameter
									type=0
								 )
			 (
				 input wire clk,
				 input wire sgn,
				 output wire out
			 );

reg sgn_pre = 0;

always @(posedge clk) begin
	if (sgn_changed) sgn_pre <= sgn;
end

assign sgn_changed = sgn ^ sgn_pre,
			 pos_edge = (type == 0) & (sgn & sgn_changed),
			 neg_edge = (type == 1) & (~sgn & sgn_changed),
			 both_edges = (type == 2) & sgn_changed,
			 out = pos_edge | neg_edge | both_edges;

endmodule

pwm.v
module pwm #(parameter
						 clk_mhz = 50,
						 freq_khz = 400,
						 duty = 40
						)
			 (
				 input wire clk,
				 input wire rst,
				 output wire out
			 );


function[31:0] div(input[31:0] A, input[31:0] B);
	begin
		div = A / B + (2*(A % B) >= B ? 1 : 0);
	end
endfunction

localparam clk_khz = 1000 * clk_mhz,
					 cnt_max = div(clk_khz, freq_khz),
					 cnt_width = $clog2(cnt_max),
					 cnt_duty = div(duty * cnt_max, 100);

reg[cnt_width-1:0] cnt = 0;

always @(posedge clk) begin
	cnt <= (~rst & (cnt < cnt_max-1)) ? cnt + 1 : 0;
end

assign out = cnt < cnt_duty;

endmodule

entry.v
/*
module entry(
				 input wire clk,
				 input wire data,
				 output reg out
			 );
 
localparam baudrate = 100_000,
					 f_clk = 50_000_000,
					 cnt_val = f_clk/(2*baudrate)-1;
 
reg isTransmit = 0;
reg data_pre = 1;
reg[13:0] cnt = cnt_val;
reg[9:0] sh_reg = 0;
 
reg[4:0] cnt2 = 0;
 
 
always @(posedge clk) begin
	if (data_negedge) begin
		data_pre <= data;
		if (~isTransmit) begin
			isTransmit <= 1;
			cnt <= 3*cnt_val;
		end
		else cnt <= cnt_val;
	end
	else if (data_posedge) begin
		data_pre <= data;
		cnt <= cnt_val;
	end
	else cnt <= cnt - 1;
end
 
always @(posedge clk) begin
	if (check) begin
		sh_reg <= sh_reg << 1;
		sh_reg[0] <= data;
	end
end
 
always @(posedge clk) begin
	if (cnt2 == 0) begin
		cnt2 <= 10 + 10*sh_reg;
		out <= out ^ 1;
	end
	else cnt2 <= cnt2 - 1;
end
 
 
assign data_posedge = data && ~data_pre;
assign data_negedge = ~data && data_pre;
assign check = isTransmit && (cnt == 0);
 
endmodule
*/


/*
module entry #(parameter width=8) (
				 input wire clk,
				 input wire data,
				 output reg[width-1:0] sh_reg
			 );
 
 
 
 
 
always @(posedge clk) begin
	sh_reg <= {sh_reg[width-2:0], data};
end
 
endmodule
*/

`include "pwm.v"
`include "edge_det.v"
`include "cnt.v"

module entry (
				 input wire clk,
				 input wire uart_tx,
				 output wire uart_clk,
				 output wire tmr_rst,
				 output wire[7:0] state_cnt_value,
				 output reg[1:0] state_value = 0,
				 output reg[7:0] info = 0
			 );

wire neg_egde_det_out;



reg zero = 0;


pwm #(.freq_khz(2000), .duty(50)) pwm_ins(.clk(clk), .rst(zero), .out(uart_clk));
//edge_det #(.type(0)) resett(.clk(clk), .sgn(uart_tx), .out(get_data));
edge_det #(.type(1)) neg_edge_det(.clk(clk), .sgn(uart_tx), .out(neg_egde_det_out));
cnt state_cnt(.clk(uart_clk), .rst(tmr_rst), .out(state_cnt_value));

always @(posedge clk) begin
	if (tmr_rst) state_value <= 1;
	else if (e2) state_value <= 2;
	else if (e3) state_value <= 0;
end

always @(posedge middle) begin
	if (state_value) info <= {uart_tx, info[7:1]};
end

assign tmr_rst = (state_value == 0) & neg_egde_det_out,
			 e2 = (state_value == 1) & (state_cnt_value == 3),
			 e3 = (state_value == 2) & (state_cnt_value == 2*7+3),
			 middle = (state_cnt_value-1)%2 == 0;


endmodule

tb.v
`timescale 1ns/1ps
`include "entry.v"

module test_entry;

reg clk, data;
wire out, edges;
wire[1:0]	state_value;
wire[7:0] out3, info;

//localparam mask = 0b0001_0000;

integer i;

//устанавливаем экземпляр тестируемого модуля
//entry entry_inst(tclk, data, out, state_value);
entry entry_inst(
				.clk(clk),
				.uart_tx(data),
				.uart_clk(out),
				.tmr_rst(edges),
				.state_cnt_value(out3),
				.state_value(state_value),
				.info(info)
			);

//моделируем сигнал тактовой частоты
always #10 clk = ~clk;

//от начала времени...

initial begin
	clk = 0;
	data = 1;

	// 0_1010_1100_1
	#1000 data = 0;	// 1250

	#1000 data = 1;
	#1000 data = 0;
	#1000 data = 1;
	#1000 data = 0;

	#1000 data = 1;
	#1000 data = 1;
	#1000 data = 0;
	#1000 data = 0;

	#1000 data = 1;
end

//заканчиваем симуляцию в момент времени "400"
initial #50000 $finish;


//создаем файл VCD для последующего анализа сигналов
initial begin
	$dumpfile("out.vcd");
	$dumpvars(0,test_entry);
end

//наблюдаем на некоторыми сигналами системы
initial $monitor($stime,, clk,,, data,, out,, state_value,, out3,, edges,, info);

endmodule

out.vcd
$date
	Sat Dec 07 19:49:44 2019
$end
$version
	Icarus Verilog
$end
$timescale
	1ps
$end
$scope module test_entry $end
$var wire 2 ! state_value [1:0] $end
$var wire 8 " out3 [7:0] $end
$var wire 1 # out $end
$var wire 8 $ info [7:0] $end
$var wire 1 % edges $end
$var reg 1 & clk $end
$var reg 1 ' data $end
$scope module entry_inst $end
$var wire 1 & clk $end
$var wire 1 ( e2 $end
$var wire 1 ) e3 $end
$var wire 1 % tmr_rst $end
$var wire 1 ' uart_tx $end
$var wire 1 # uart_clk $end
$var wire 8 * state_cnt_value [7:0] $end
$var wire 1 + neg_egde_det_out $end
$var wire 1 , middle $end
$var reg 8 - info [7:0] $end
$var reg 2 . state_value [1:0] $end
$var reg 1 / zero $end
$scope module neg_edge_det $end
$var wire 1 0 both_edges $end
$var wire 1 & clk $end
$var wire 1 1 neg_edge $end
$var wire 1 + out $end
$var wire 1 2 pos_edge $end
$var wire 1 ' sgn $end
$var wire 1 3 sgn_changed $end
$var reg 1 4 sgn_pre $end
$upscope $end
$scope module pwm_ins $end
$var wire 1 & clk $end
$var wire 1 / rst $end
$var wire 1 # out $end
$var reg 5 5 cnt [4:0] $end
$scope function div $end
$var reg 32 6 A [31:0] $end
$var reg 32 7 B [31:0] $end
$upscope $end
$upscope $end
$scope module state_cnt $end
$var wire 1 # clk $end
$var wire 1 % rst $end
$var reg 8 8 out [7:0] $end
$upscope $end
$upscope $end
$upscope $end
$enddefinitions $end
#0
$dumpvars
b0 8
bx 7
bx 6
b0 5
04
13
02
01
00
0/
b0 .
b0 -
0,
0+
b0 *
0)
0(
1'
0&
0%
b0 $
1#
b0 "
b0 !
$end
#10000
03
b1 5
14
1&
#20000
0&
#30000
b10 5
1&
#40000
0&
#50000
b11 5
1&
#60000
0&
#70000
b100 5
1&
#80000
0&
#90000
b101 5
1&
#100000
0&
#110000
b110 5
1&
#120000
0&
#130000
b111 5
1&
#140000
0&
#150000
b1000 5
1&
#160000
0&
#170000
b1001 5
1&
#180000
0&
#190000
b1010 5
1&
#200000
0&
#210000
b1011 5
1&
#220000
0&
#230000
b1100 5
1&
#240000
0&
#250000
0#
b1101 5
1&
#260000
0&
#270000
b1110 5
1&
#280000
0&
#290000
b1111 5
1&
#300000
0&
#310000
b10000 5
1&
#320000
0&
#330000
b10001 5
1&
#340000
0&
#350000
b10010 5
1&
#360000
0&
#370000
b10011 5
1&
#380000
0&
#390000
b10100 5
1&
#400000
0&
#410000
b10101 5
1&
#420000
0&
#430000
b10110 5
1&
#440000
0&
#450000
b10111 5
1&
#460000
0&
#470000
b11000 5
1&
#480000
0&
#490000
1,
b1 "
b1 *
b1 8
1#
b0 5
1&
#500000
0&
#510000
b1 5
1&
#520000
0&
#530000
b10 5
1&
#540000
0&
#550000
b11 5
1&
#560000
0&
#570000
b100 5
1&
#580000
0&
#590000
b101 5
1&
#600000
0&
#610000
b110 5
1&
#620000
0&
#630000
b111 5
1&
#640000
0&
#650000
b1000 5
1&
#660000
0&
#670000
b1001 5
1&
#680000
0&
#690000
b1010 5
1&
#700000
0&
#710000
b1011 5
1&
#720000
0&
#730000
b1100 5
1&
#740000
0&
#750000
0#
b1101 5
1&
#760000
0&
#770000
b1110 5
1&
#780000
0&
#790000
b1111 5
1&
#800000
0&
#810000
b10000 5
1&
#820000
0&
#830000
b10001 5
1&
#840000
0&
#850000
b10010 5
1&
#860000
0&
#870000
b10011 5
1&
#880000
0&
#890000
b10100 5
1&
#900000
0&
#910000
b10101 5
1&
#920000
0&
#930000
b10110 5
1&
#940000
0&
#950000
b10111 5
1&
#960000
0&
#970000
b11000 5
1&
#980000
0&
#990000
0,
b10 "
b10 *
b10 8
1#
b0 5
1&
#1000000
b0 "
b0 *
b0 8
1%
1+
11
13
0&
0'
#1010000
0+
01
03
0%
b1 5
04
b1 !
b1 .
1&
#1020000
0&
#1030000
b10 5
1&
#1040000
0&
#1050000
b11 5
1&
#1060000
0&
#1070000
b100 5
1&
#1080000
0&
#1090000
b101 5
1&
#1100000
0&
#1110000
b110 5
1&
#1120000
0&
#1130000
b111 5
1&
#1140000
0&
#1150000
b1000 5
1&
#1160000
0&
#1170000
b1001 5
1&
#1180000
0&
#1190000
b1010 5
1&
#1200000
0&
#1210000
b1011 5
1&
#1220000
0&
#1230000
b1100 5
1&
#1240000
0&
#1250000
0#
b1101 5
1&
#1260000
0&
#1270000
b1110 5
1&
#1280000
0&
#1290000
b1111 5
1&
#1300000
0&
#1310000
b10000 5
1&
#1320000
0&
#1330000
b10001 5
1&
#1340000
0&
#1350000
b10010 5
1&
#1360000
0&
#1370000
b10011 5
1&
#1380000
0&
#1390000
b10100 5
1&
#1400000
0&
#1410000
b10101 5
1&
#1420000
0&
#1430000
b10110 5
1&
#1440000
0&
#1450000
b10111 5
1&
#1460000
0&
#1470000
b11000 5
1&
#1480000
0&
#1490000
1,
b1 "
b1 *
b1 8
1#
b0 5
1&
#1500000
0&
#1510000
b1 5
1&
#1520000
0&
#1530000
b10 5
1&
#1540000
0&
#1550000
b11 5
1&
#1560000
0&
#1570000
b100 5
1&
#1580000
0&
#1590000
b101 5
1&
#1600000
0&
#1610000
b110 5
1&
#1620000
0&
#1630000
b111 5
1&
#1640000
0&
#1650000
b1000 5
1&
#1660000
0&
#1670000
b1001 5
1&
#1680000
0&
#1690000
b1010 5
1&
#1700000
0&
#1710000
b1011 5
1&
#1720000
0&
#1730000
b1100 5
1&
#1740000
0&
#1750000
0#
b1101 5
1&
#1760000
0&
#1770000
b1110 5
1&
#1780000
0&
#1790000
b1111 5
1&
#1800000
0&
#1810000
b10000 5
1&
#1820000
0&
#1830000
b10001 5
1&
#1840000
0&
#1850000
b10010 5
1&
#1860000
0&
#1870000
b10011 5
1&
#1880000
0&
#1890000
b10100 5
1&
#1900000
0&
#1910000
b10101 5
1&
#1920000
0&
#1930000
b10110 5
1&
#1940000
0&
#1950000
b10111 5
1&
#1960000
0&
#1970000
b11000 5
1&
#1980000
0&
#1990000
0,
b10 "
b10 *
b10 8
1#
b0 5
1&
#2000000
13
0&
1'
#2010000
03
b1 5
14
1&
#2020000
0&
#2030000
b10 5
1&
#2040000
0&
#2050000
b11 5
1&
#2060000
0&
#2070000
b100 5
1&
#2080000
0&
#2090000
b101 5
1&
#2100000
0&
#2110000
b110 5
1&
#2120000
0&
#2130000
b111 5
1&
#2140000
0&
#2150000
b1000 5
1&
#2160000
0&
#2170000
b1001 5
1&
#2180000
0&
#2190000
b1010 5
1&
#2200000
0&
#2210000
b1011 5
1&
#2220000
0&
#2230000
b1100 5
1&
#2240000
0&
#2250000
0#
b1101 5
1&
#2260000
0&
#2270000
b1110 5
1&
#2280000
0&
#2290000
b1111 5
1&
#2300000
0&
#2310000
b10000 5
1&
#2320000
0&
#2330000
b10001 5
1&
#2340000
0&
#2350000
b10010 5
1&
#2360000
0&
#2370000
b10011 5
1&
#2380000
0&
#2390000
b10100 5
1&
#2400000
0&
#2410000
b10101 5
1&
#2420000
0&
#2430000
b10110 5
1&
#2440000
0&
#2450000
b10111 5
1&
#2460000
0&
#2470000
b11000 5
1&
#2480000
0&
#2490000
b10000000 $
b10000000 -
1(
1,
b11 "
b11 *
b11 8
1#
b0 5
1&
#2500000
0&
#2510000
0(
b10 !
b10 .
b1 5
1&
#2520000
0&
#2530000
b10 5
1&
#2540000
0&
#2550000
b11 5
1&
#2560000
0&
#2570000
b100 5
1&
#2580000
0&
#2590000
b101 5
1&
#2600000
0&
#2610000
b110 5
1&
#2620000
0&
#2630000
b111 5
1&
#2640000
0&
#2650000
b1000 5
1&
#2660000
0&
#2670000
b1001 5
1&
#2680000
0&
#2690000
b1010 5
1&
#2700000
0&
#2710000
b1011 5
1&
#2720000
0&
#2730000
b1100 5
1&
#2740000
0&
#2750000
0#
b1101 5
1&
#2760000
0&
#2770000
b1110 5
1&
#2780000
0&
#2790000
b1111 5
1&
#2800000
0&
#2810000
b10000 5
1&
#2820000
0&
#2830000
b10001 5
1&
#2840000
0&
#2850000
b10010 5
1&
#2860000
0&
#2870000
b10011 5
1&
#2880000
0&
#2890000
b10100 5
1&
#2900000
0&
#2910000
b10101 5
1&
#2920000
0&
#2930000
b10110 5
1&
#2940000
0&
#2950000
b10111 5
1&
#2960000
0&
#2970000
b11000 5
1&
#2980000
0&
#2990000
0,
b100 "
b100 *
b100 8
1#
b0 5
1&
#3000000
1+
11
13
0&
0'
#3010000
0+
01
03
b1 5
04
1&
#3020000
0&
#3030000
b10 5
1&
#3040000
0&
#3050000
b11 5
1&
#3060000
0&
#3070000
b100 5
1&
#3080000
0&
#3090000
b101 5
1&
#3100000
0&
#3110000
b110 5
1&
#3120000
0&
#3130000
b111 5
1&
#3140000
0&
#3150000
b1000 5
1&
#3160000
0&
#3170000
b1001 5
1&
#3180000
0&
#3190000
b1010 5
1&
#3200000
0&
#3210000
b1011 5
1&
#3220000
0&
#3230000
b1100 5
1&
#3240000
0&
#3250000
0#
b1101 5
1&
#3260000
0&
#3270000
b1110 5
1&
#3280000
0&
#3290000
b1111 5
1&
#3300000
0&
#3310000
b10000 5
1&
#3320000
0&
#3330000
b10001 5
1&
#3340000
0&
#3350000
b10010 5
1&
#3360000
0&
#3370000
b10011 5
1&
#3380000
0&
#3390000
b10100 5
1&
#3400000
0&
#3410000
b10101 5
1&
#3420000
0&
#3430000
b10110 5
1&
#3440000
0&
#3450000
b10111 5
1&
#3460000
0&
#3470000
b11000 5
1&
#3480000
0&
#3490000
b1000000 $
b1000000 -
1,
b101 "
b101 *
b101 8
1#
b0 5
1&
#3500000
0&
#3510000
b1 5
1&
#3520000
0&
#3530000
b10 5
1&
#3540000
0&
#3550000
b11 5
1&
#3560000
0&
#3570000
b100 5
1&
#3580000
0&
#3590000
b101 5
1&
#3600000
0&
#3610000
b110 5
1&
#3620000
0&
#3630000
b111 5
1&
#3640000
0&
#3650000
b1000 5
1&
#3660000
0&
#3670000
b1001 5
1&
#3680000
0&
#3690000
b1010 5
1&
#3700000
0&
#3710000
b1011 5
1&
#3720000
0&
#3730000
b1100 5
1&
#3740000
0&
#3750000
0#
b1101 5
1&
#3760000
0&
#3770000
b1110 5
1&
#3780000
0&
#3790000
b1111 5
1&
#3800000
0&
#3810000
b10000 5
1&
#3820000
0&
#3830000
b10001 5
1&
#3840000
0&
#3850000
b10010 5
1&
#3860000
0&
#3870000
b10011 5
1&
#3880000
0&
#3890000
b10100 5
1&
#3900000
0&
#3910000
b10101 5
1&
#3920000
0&
#3930000
b10110 5
1&
#3940000
0&
#3950000
b10111 5
1&
#3960000
0&
#3970000
b11000 5
1&
#3980000
0&
#3990000
0,
b110 "
b110 *
b110 8
1#
b0 5
1&
#4000000
13
0&
1'
#4010000
03
b1 5
14
1&
#4020000
0&
#4030000
b10 5
1&
#4040000
0&
#4050000
b11 5
1&
#4060000
0&
#4070000
b100 5
1&
#4080000
0&
#4090000
b101 5
1&
#4100000
0&
#4110000
b110 5
1&
#4120000
0&
#4130000
b111 5
1&
#4140000
0&
#4150000
b1000 5
1&
#4160000
0&
#4170000
b1001 5
1&
#4180000
0&
#4190000
b1010 5
1&
#4200000
0&
#4210000
b1011 5
1&
#4220000
0&
#4230000
b1100 5
1&
#4240000
0&
#4250000
0#
b1101 5
1&
#4260000
0&
#4270000
b1110 5
1&
#4280000
0&
#4290000
b1111 5
1&
#4300000
0&
#4310000
b10000 5
1&
#4320000
0&
#4330000
b10001 5
1&
#4340000
0&
#4350000
b10010 5
1&
#4360000
0&
#4370000
b10011 5
1&
#4380000
0&
#4390000
b10100 5
1&
#4400000
0&
#4410000
b10101 5
1&
#4420000
0&
#4430000
b10110 5
1&
#4440000
0&
#4450000
b10111 5
1&
#4460000
0&
#4470000
b11000 5
1&
#4480000
0&
#4490000
b10100000 $
b10100000 -
1,
b111 "
b111 *
b111 8
1#
b0 5
1&
#4500000
0&
#4510000
b1 5
1&
#4520000
0&
#4530000
b10 5
1&
#4540000
0&
#4550000
b11 5
1&
#4560000
0&
#4570000
b100 5
1&
#4580000
0&
#4590000
b101 5
1&
#4600000
0&
#4610000
b110 5
1&
#4620000
0&
#4630000
b111 5
1&
#4640000
0&
#4650000
b1000 5
1&
#4660000
0&
#4670000
b1001 5
1&
#4680000
0&
#4690000
b1010 5
1&
#4700000
0&
#4710000
b1011 5
1&
#4720000
0&
#4730000
b1100 5
1&
#4740000
0&
#4750000
0#
b1101 5
1&
#4760000
0&
#4770000
b1110 5
1&
#4780000
0&
#4790000
b1111 5
1&
#4800000
0&
#4810000
b10000 5
1&
#4820000
0&
#4830000
b10001 5
1&
#4840000
0&
#4850000
b10010 5
1&
#4860000
0&
#4870000
b10011 5
1&
#4880000
0&
#4890000
b10100 5
1&
#4900000
0&
#4910000
b10101 5
1&
#4920000
0&
#4930000
b10110 5
1&
#4940000
0&
#4950000
b10111 5
1&
#4960000
0&
#4970000
b11000 5
1&
#4980000
0&
#4990000
0,
b1000 "
b1000 *
b1000 8
1#
b0 5
1&
#5000000
1+
11
13
0&
0'
#5010000
0+
01
03
b1 5
04
1&
#5020000
0&
#5030000
b10 5
1&
#5040000
0&
#5050000
b11 5
1&
#5060000
0&
#5070000
b100 5
1&
#5080000
0&
#5090000
b101 5
1&
#5100000
0&
#5110000
b110 5
1&
#5120000
0&
#5130000
b111 5
1&
#5140000
0&
#5150000
b1000 5
1&
#5160000
0&
#5170000
b1001 5
1&
#5180000
0&
#5190000
b1010 5
1&
#5200000
0&
#5210000
b1011 5
1&
#5220000
0&
#5230000
b1100 5
1&
#5240000
0&
#5250000
0#
b1101 5
1&
#5260000
0&
#5270000
b1110 5
1&
#5280000
0&
#5290000
b1111 5
1&
#5300000
0&
#5310000
b10000 5
1&
#5320000
0&
#5330000
b10001 5
1&
#5340000
0&
#5350000
b10010 5
1&
#5360000
0&
#5370000
b10011 5
1&
#5380000
0&
#5390000
b10100 5
1&
#5400000
0&
#5410000
b10101 5
1&
#5420000
0&
#5430000
b10110 5
1&
#5440000
0&
#5450000
b10111 5
1&
#5460000
0&
#5470000
b11000 5
1&
#5480000
0&
#5490000
b1010000 $
b1010000 -
1,
b1001 "
b1001 *
b1001 8
1#
b0 5
1&
#5500000
0&
#5510000
b1 5
1&
#5520000
0&
#5530000
b10 5
1&
#5540000
0&
#5550000
b11 5
1&
#5560000
0&
#5570000
b100 5
1&
#5580000
0&
#5590000
b101 5
1&
#5600000
0&
#5610000
b110 5
1&
#5620000
0&
#5630000
b111 5
1&
#5640000
0&
#5650000
b1000 5
1&
#5660000
0&
#5670000
b1001 5
1&
#5680000
0&
#5690000
b1010 5
1&
#5700000
0&
#5710000
b1011 5
1&
#5720000
0&
#5730000
b1100 5
1&
#5740000
0&
#5750000
0#
b1101 5
1&
#5760000
0&
#5770000
b1110 5
1&
#5780000
0&
#5790000
b1111 5
1&
#5800000
0&
#5810000
b10000 5
1&
#5820000
0&
#5830000
b10001 5
1&
#5840000
0&
#5850000
b10010 5
1&
#5860000
0&
#5870000
b10011 5
1&
#5880000
0&
#5890000
b10100 5
1&
#5900000
0&
#5910000
b10101 5
1&
#5920000
0&
#5930000
b10110 5
1&
#5940000
0&
#5950000
b10111 5
1&
#5960000
0&
#5970000
b11000 5
1&
#5980000
0&
#5990000
0,
b1010 "
b1010 *
b1010 8
1#
b0 5
1&
#6000000
13
0&
1'
#6010000
03
b1 5
14
1&
#6020000
0&
#6030000
b10 5
1&
#6040000
0&
#6050000
b11 5
1&
#6060000
0&
#6070000
b100 5
1&
#6080000
0&
#6090000
b101 5
1&
#6100000
0&
#6110000
b110 5
1&
#6120000
0&
#6130000
b111 5
1&
#6140000
0&
#6150000
b1000 5
1&
#6160000
0&
#6170000
b1001 5
1&
#6180000
0&
#6190000
b1010 5
1&
#6200000
0&
#6210000
b1011 5
1&
#6220000
0&
#6230000
b1100 5
1&
#6240000
0&
#6250000
0#
b1101 5
1&
#6260000
0&
#6270000
b1110 5
1&
#6280000
0&
#6290000
b1111 5
1&
#6300000
0&
#6310000
b10000 5
1&
#6320000
0&
#6330000
b10001 5
1&
#6340000
0&
#6350000
b10010 5
1&
#6360000
0&
#6370000
b10011 5
1&
#6380000
0&
#6390000
b10100 5
1&
#6400000
0&
#6410000
b10101 5
1&
#6420000
0&
#6430000
b10110 5
1&
#6440000
0&
#6450000
b10111 5
1&
#6460000
0&
#6470000
b11000 5
1&
#6480000
0&
#6490000
b10101000 $
b10101000 -
1,
b1011 "
b1011 *
b1011 8
1#
b0 5
1&
#6500000
0&
#6510000
b1 5
1&
#6520000
0&
#6530000
b10 5
1&
#6540000
0&
#6550000
b11 5
1&
#6560000
0&
#6570000
b100 5
1&
#6580000
0&
#6590000
b101 5
1&
#6600000
0&
#6610000
b110 5
1&
#6620000
0&
#6630000
b111 5
1&
#6640000
0&
#6650000
b1000 5
1&
#6660000
0&
#6670000
b1001 5
1&
#6680000
0&
#6690000
b1010 5
1&
#6700000
0&
#6710000
b1011 5
1&
#6720000
0&
#6730000
b1100 5
1&
#6740000
0&
#6750000
0#
b1101 5
1&
#6760000
0&
#6770000
b1110 5
1&
#6780000
0&
#6790000
b1111 5
1&
#6800000
0&
#6810000
b10000 5
1&
#6820000
0&
#6830000
b10001 5
1&
#6840000
0&
#6850000
b10010 5
1&
#6860000
0&
#6870000
b10011 5
1&
#6880000
0&
#6890000
b10100 5
1&
#6900000
0&
#6910000
b10101 5
1&
#6920000
0&
#6930000
b10110 5
1&
#6940000
0&
#6950000
b10111 5
1&
#6960000
0&
#6970000
b11000 5
1&
#6980000
0&
#6990000
0,
b1100 "
b1100 *
b1100 8
1#
b0 5
1&
#7000000
0&
#7010000
b1 5
1&
#7020000
0&
#7030000
b10 5
1&
#7040000
0&
#7050000
b11 5
1&
#7060000
0&
#7070000
b100 5
1&
#7080000
0&
#7090000
b101 5
1&
#7100000
0&
#7110000
b110 5
1&
#7120000
0&
#7130000
b111 5
1&
#7140000
0&
#7150000
b1000 5
1&
#7160000
0&
#7170000
b1001 5
1&
#7180000
0&
#7190000
b1010 5
1&
#7200000
0&
#7210000
b1011 5
1&
#7220000
0&
#7230000
b1100 5
1&
#7240000
0&
#7250000
0#
b1101 5
1&
#7260000
0&
#7270000
b1110 5
1&
#7280000
0&
#7290000
b1111 5
1&
#7300000
0&
#7310000
b10000 5
1&
#7320000
0&
#7330000
b10001 5
1&
#7340000
0&
#7350000
b10010 5
1&
#7360000
0&
#7370000
b10011 5
1&
#7380000
0&
#7390000
b10100 5
1&
#7400000
0&
#7410000
b10101 5
1&
#7420000
0&
#7430000
b10110 5
1&
#7440000
0&
#7450000
b10111 5
1&
#7460000
0&
#7470000
b11000 5
1&
#7480000
0&
#7490000
b11010100 $
b11010100 -
1,
b1101 "
b1101 *
b1101 8
1#
b0 5
1&
#7500000
0&
#7510000
b1 5
1&
#7520000
0&
#7530000
b10 5
1&
#7540000
0&
#7550000
b11 5
1&
#7560000
0&
#7570000
b100 5
1&
#7580000
0&
#7590000
b101 5
1&
#7600000
0&
#7610000
b110 5
1&
#7620000
0&
#7630000
b111 5
1&
#7640000
0&
#7650000
b1000 5
1&
#7660000
0&
#7670000
b1001 5
1&
#7680000
0&
#7690000
b1010 5
1&
#7700000
0&
#7710000
b1011 5
1&
#7720000
0&
#7730000
b1100 5
1&
#7740000
0&
#7750000
0#
b1101 5
1&
#7760000
0&
#7770000
b1110 5
1&
#7780000
0&
#7790000
b1111 5
1&
#7800000
0&
#7810000
b10000 5
1&
#7820000
0&
#7830000
b10001 5
1&
#7840000
0&
#7850000
b10010 5
1&
#7860000
0&
#7870000
b10011 5
1&
#7880000
0&
#7890000
b10100 5
1&
#7900000
0&
#7910000
b10101 5
1&
#7920000
0&
#7930000
b10110 5
1&
#7940000
0&
#7950000
b10111 5
1&
#7960000
0&
#7970000
b11000 5
1&
#7980000
0&
#7990000
0,
b1110 "
b1110 *
b1110 8
1#
b0 5
1&
#8000000
1+
11
13
0&
0'
#8010000
0+
01
03
b1 5
04
1&
#8020000
0&
#8030000
b10 5
1&
#8040000
0&
#8050000
b11 5
1&
#8060000
0&
#8070000
b100 5
1&
#8080000
0&
#8090000
b101 5
1&
#8100000
0&
#8110000
b110 5
1&
#8120000
0&
#8130000
b111 5
1&
#8140000
0&
#8150000
b1000 5
1&
#8160000
0&
#8170000
b1001 5
1&
#8180000
0&
#8190000
b1010 5
1&
#8200000
0&
#8210000
b1011 5
1&
#8220000
0&
#8230000
b1100 5
1&
#8240000
0&
#8250000
0#
b1101 5
1&
#8260000
0&
#8270000
b1110 5
1&
#8280000
0&
#8290000
b1111 5
1&
#8300000
0&
#8310000
b10000 5
1&
#8320000
0&
#8330000
b10001 5
1&
#8340000
0&
#8350000
b10010 5
1&
#8360000
0&
#8370000
b10011 5
1&
#8380000
0&
#8390000
b10100 5
1&
#8400000
0&
#8410000
b10101 5
1&
#8420000
0&
#8430000
b10110 5
1&
#8440000
0&
#8450000
b10111 5
1&
#8460000
0&
#8470000
b11000 5
1&
#8480000
0&
#8490000
b1101010 $
b1101010 -
1,
b1111 "
b1111 *
b1111 8
1#
b0 5
1&
#8500000
0&
#8510000
b1 5
1&
#8520000
0&
#8530000
b10 5
1&
#8540000
0&
#8550000
b11 5
1&
#8560000
0&
#8570000
b100 5
1&
#8580000
0&
#8590000
b101 5
1&
#8600000
0&
#8610000
b110 5
1&
#8620000
0&
#8630000
b111 5
1&
#8640000
0&
#8650000
b1000 5
1&
#8660000
0&
#8670000
b1001 5
1&
#8680000
0&
#8690000
b1010 5
1&
#8700000
0&
#8710000
b1011 5
1&
#8720000
0&
#8730000
b1100 5
1&
#8740000
0&
#8750000
0#
b1101 5
1&
#8760000
0&
#8770000
b1110 5
1&
#8780000
0&
#8790000
b1111 5
1&
#8800000
0&
#8810000
b10000 5
1&
#8820000
0&
#8830000
b10001 5
1&
#8840000
0&
#8850000
b10010 5
1&
#8860000
0&
#8870000
b10011 5
1&
#8880000
0&
#8890000
b10100 5
1&
#8900000
0&
#8910000
b10101 5
1&
#8920000
0&
#8930000
b10110 5
1&
#8940000
0&
#8950000
b10111 5
1&
#8960000
0&
#8970000
b11000 5
1&
#8980000
0&
#8990000
0,
b10000 "
b10000 *
b10000 8
1#
b0 5
1&
#9000000
0&
#9010000
b1 5
1&
#9020000
0&
#9030000
b10 5
1&
#9040000
0&
#9050000
b11 5
1&
#9060000
0&
#9070000
b100 5
1&
#9080000
0&
#9090000
b101 5
1&
#9100000
0&
#9110000
b110 5
1&
#9120000
0&
#9130000
b111 5
1&
#9140000
0&
#9150000
b1000 5
1&
#9160000
0&
#9170000
b1001 5
1&
#9180000
0&
#9190000
b1010 5
1&
#9200000
0&
#9210000
b1011 5
1&
#9220000
0&
#9230000
b1100 5
1&
#9240000
0&
#9250000
0#
b1101 5
1&
#9260000
0&
#9270000
b1110 5
1&
#9280000
0&
#9290000
b1111 5
1&
#9300000
0&
#9310000
b10000 5
1&
#9320000
0&
#9330000
b10001 5
1&
#9340000
0&
#9350000
b10010 5
1&
#9360000
0&
#9370000
b10011 5
1&
#9380000
0&
#9390000
b10100 5
1&
#9400000
0&
#9410000
b10101 5
1&
#9420000
0&
#9430000
b10110 5
1&
#9440000
0&
#9450000
b10111 5
1&
#9460000
0&
#9470000
b11000 5
1&
#9480000
0&
#9490000
b110101 $
b110101 -
1)
1,
b10001 "
b10001 *
b10001 8
1#
b0 5
1&
#9500000
0&
#9510000
0)
b0 !
b0 .
b1 5
1&
#9520000
0&
#9530000
b10 5
1&
#9540000
0&
#9550000
b11 5
1&
#9560000
0&
#9570000
b100 5
1&
#9580000
0&
#9590000
b101 5
1&
#9600000
0&
#9610000
b110 5
1&
#9620000
0&
#9630000
b111 5
1&
#9640000
0&
#9650000
b1000 5
1&
#9660000
0&
#9670000
b1001 5
1&
#9680000
0&
#9690000
b1010 5
1&
#9700000
0&
#9710000
b1011 5
1&
#9720000
0&
#9730000
b1100 5
1&
#9740000
0&
#9750000
0#
b1101 5
1&
#9760000
0&
#9770000
b1110 5
1&
#9780000
0&
#9790000
b1111 5
1&
#9800000
0&
#9810000
b10000 5
1&
#9820000
0&
#9830000
b10001 5
1&
#9840000
0&
#9850000
b10010 5
1&
#9860000
0&
#9870000
b10011 5
1&
#9880000
0&
#9890000
b10100 5
1&
#9900000
0&
#9910000
b10101 5
1&
#9920000
0&
#9930000
b10110 5
1&
#9940000
0&
#9950000
b10111 5
1&
#9960000
0&
#9970000
b11000 5
1&
#9980000
0&
#9990000
0,
b10010 "
b10010 *
b10010 8
1#
b0 5
1&
#10000000
13
0&
1'
#10010000
03
b1 5
14
1&
#10020000
0&
#10030000
b10 5
1&
#10040000
0&
#10050000
b11 5
1&
#10060000
0&
#10070000
b100 5
1&
#10080000
0&
#10090000
b101 5
1&
#10100000
0&
#10110000
b110 5
1&
#10120000
0&
