entry.v
/*
module entry(
				 input wire clk,
				 input wire data,
				 output reg out
			 );
 
localparam baudrate = 100_000,
					 f_clk = 50_000_000,
					 cnt_val = f_clk/(2*baudrate)-1;
 
reg isTransmit = 0;
reg data_pre = 1;
reg[13:0] cnt = cnt_val;
reg[9:0] sh_reg = 0;
 
reg[4:0] cnt2 = 0;
 
 
always @(posedge clk) begin
	if (data_negedge) begin
		data_pre <= data;
		if (~isTransmit) begin
			isTransmit <= 1;
			cnt <= 3*cnt_val;
		end
		else cnt <= cnt_val;
	end
	else if (data_posedge) begin
		data_pre <= data;
		cnt <= cnt_val;
	end
	else cnt <= cnt - 1;
end
 
always @(posedge clk) begin
	if (check) begin
		sh_reg <= sh_reg << 1;
		sh_reg[0] <= data;
	end
end
 
always @(posedge clk) begin
	if (cnt2 == 0) begin
		cnt2 <= 10 + 10*sh_reg;
		out <= out ^ 1;
	end
	else cnt2 <= cnt2 - 1;
end
 
 
assign data_posedge = data && ~data_pre;
assign data_negedge = ~data && data_pre;
assign check = isTransmit && (cnt == 0);
 
endmodule
*/

module entry(
				 input wire clk,
				 input wire data,
				 output reg out
			 );

localparam cnt = 15;

always @(posedge clk) begin
	out <= data;
end


endmodule

tb.v
`include "entry.v"

module test_entry;

reg tclk, tdata;
wire tout;

integer i;

//устанавливаем экземпляр тестируемого модуля
entry entry_inst(tclk, tdata, tout);

//моделируем сигнал тактовой частоты
always #10 tclk = ~tclk;

//от начала времени...

initial begin
	tclk = 0;
	tdata = 0;

	#55 tdata = ~tdata;
	for (i=0; i<8; i++) #50 tdata = ~tdata;
end

//заканчиваем симуляцию в момент времени "400"
initial #500 $finish;


//создаем файл VCD для последующего анализа сигналов
initial begin
	$dumpfile("out.vcd");
	$dumpvars(0,test_entry);
end

//наблюдаем на некоторыми сигналами системы
initial $monitor($stime,, tclk,,, tdata,, tout);

endmodule

out.vcd
$date
	Mon Nov 25 22:05:52 2019
$end
$version
	Icarus Verilog
$end
$timescale
	1s
$end
$scope module test_entry $end
$var wire 1 ! tout $end
$var reg 1 " tclk $end
$var reg 1 # tdata $end
$var integer 32 $ i [31:0] $end
$scope module entry_inst $end
$var wire 1 " clk $end
$var wire 1 # data $end
$var reg 1 ! out $end
$upscope $end
$upscope $end
$enddefinitions $end
#0
$dumpvars
bx $
0#
0"
x!
$end
#10
0!
1"
#20
0"
#30
1"
#40
0"
#50
1"
#55
b0 $
1#
#60
0"
#70
1!
1"
#80
0"
#90
1"
#100
0"
#105
b1 $
0#
#110
0!
1"
#120
0"
#130
1"
#140
0"
#150
1"
#155
b10 $
1#
#160
0"
#170
1!
1"
#180
0"
#190
1"
#200
0"
#205
b11 $
0#
#210
0!
1"
#220
0"
#230
1"
#240
0"
#250
1"
#255
b100 $
1#
#260
0"
#270
1!
1"
#280
0"
#290
1"
#300
0"
#305
b101 $
0#
#310
0!
1"
#320
0"
#330
1"
#340
0"
#350
1"
#355
b110 $
1#
#360
0"
#370
1!
1"
#380
0"
#390
1"
#400
0"
#405
b111 $
0#
#410
0!
1"
#420
0"
#430
1"
#440
0"
#450
1"
#455
b1000 $
1#
#460
0"
#470
1!
1"
